{
    "prepare_queue": {
        "installed": [],
        "uninstalled": []
    },
    "config_munge": {
        "files": {}
    },
    "installed_plugins": {
        "cordova-plugin-whitelist": {
            "PACKAGE_NAME": "com.dtech.cordova.meth"
        },
        "cordova-plugin-admobpro": {
            "PACKAGE_NAME": "com.dtech.cordova.meth"
        },
        "cordova-plugin-device": {
            "PACKAGE_NAME": "com.dtech.cordova.meth"
        },
        "cordova-plugin-splashscreen": {
            "PACKAGE_NAME": "com.dtech.cordova.meth"
        }
    },
    "dependent_plugins": {
        "cordova-plugin-extension": {
            "PACKAGE_NAME": "com.dtech.cordova.meth"
        }
    }
}